pyllector/__init__.py
pyllector/models.py
pyllector/pyllector.py
pyllector-0.0.6.dist-info/METADATA
pyllector-0.0.6.dist-info/WHEEL
pyllector-0.0.6.dist-info/top_level.txt
pyllector-0.0.6.dist-info/RECORD
