Metadata-Version: 2.1
Name: pyllector
Version: 0.0.6
Summary: Simple api collector
Home-page: https://github.com/KolesniCow/pyllector
Author: Billy Dumplington
Author-email: feedfeed369@gmail.com
Project-URL: Bug Tracker, https://github.com/KolesniCow/pyllector/issues
Classifier: Programming Language :: Python :: 3
Classifier: License :: OSI Approved :: MIT License
Classifier: Operating System :: OS Independent
Requires-Python: >=3.10
